pairwise_testing/__init__.py
pairwise_testing/pairwise_testing.py
yapairwise_testing/__init__.py
yapairwise_testing/pairwise_testing.py
yapairwise_testing-0.2.dist-info/LICENSE.txt
yapairwise_testing-0.2.dist-info/METADATA
yapairwise_testing-0.2.dist-info/WHEEL
yapairwise_testing-0.2.dist-info/top_level.txt
yapairwise_testing-0.2.dist-info/RECORD
