Metadata-Version: 2.1
Name: yapairwise-testing
Version: 0.2
Summary: A library for pairwise testing package
Home-page: https://github.com/claytonfraga/yapairwise_testing
Author: Clayton Vieira Fraga Filho
Author-email: claytonfraga@gmail.com
License: MIT
Platform: UNKNOWN
Classifier: License :: OSI Approved :: MIT License
Classifier: Programming Language :: Python :: 3.8
Requires-Python: >=3.6
License-File: LICENSE.txt
